{
    "env": {
        "pythonVersion": "3.11",
        "cudaVersion": "11.7"
    },
    "configurations": [
        {
            "name": "Linux",
            "includePath": [
                "/usr/include/python${pythonVersion}",
                "${workspaceFolder}/.env/lib/python${pythonVersion}/site-packages/torch/include",
                "${workspaceFolder}/.env/lib/python${pythonVersion}/site-packages/torch/include/torch/csrc/api/include"
            ],
            "defines": [],
            "compilerPath": "/usr/local/cuda-${cudaVersion}/bin/nvcc",
            "cppStandard": "c++11",
            "intelliSenseMode": "linux-gcc-x64",
            "configurationProvider": "ms-vscode.cpptools"
        }
    ],
    "version": 4
}
